.DS_Store
stormkit/.DS_Store
stormkit/__init__.py
stormkit/sentimentAnalysis.py
stormkit/lists/.DS_Store
stormkit/lists/angry-lex.txt
stormkit/lists/authors.txt
stormkit/lists/neg-lex-strip.txt
stormkit/lists/pos-lex-strip.txt
stormkit/lists/sad-lex.txt
stormkit/lists/scared-lex.txt
stormkit/lists/worried-lex.txt
stormkit-1.0.4.dist-info/.DS_Store
stormkit-1.0.4.dist-info/DESCRIPTION.rst
stormkit-1.0.4.dist-info/METADATA
stormkit-1.0.4.dist-info/RECORD
stormkit-1.0.4.dist-info/WHEEL
stormkit-1.0.4.dist-info/metadata.json
stormkit-1.0.4.dist-info/top_level.txt
