Metadata-Version: 2.0
Name: stormkit
Version: 1.0.4
Summary: A collection of tools for metadata analysis and generative art.
Home-page: https://github.com/joemcalister/stormkit
Author: Joe McAlister
Author-email: joe@lonestorm.com
License: MIT
Keywords: sentiment anlayisis multi mood
Platform: UNKNOWN
Classifier: Development Status :: 4 - Beta
Classifier: Intended Audience :: Developers
Classifier: Topic :: Software Development :: Build Tools
Classifier: License :: OSI Approved :: MIT License
Classifier: Programming Language :: Python :: 2
Classifier: Programming Language :: Python :: 2.7
Classifier: Programming Language :: Python :: 3
Classifier: Programming Language :: Python :: 3.3
Classifier: Programming Language :: Python :: 3.4
Classifier: Programming Language :: Python :: 3.5
